MANIFEST.in
setup.py
ppanini/__init__.py
ppanini/config.py
ppanini/ppanini.py
ppanini/utilities.py
ppanini.egg-info/PKG-INFO
ppanini.egg-info/SOURCES.txt
ppanini.egg-info/dependency_links.txt
ppanini.egg-info/entry_points.txt
ppanini.egg-info/not-zip-safe
ppanini.egg-info/top_level.txt
ppanini/data/map_uniref90_infogo1000.txt.gz
ppanini/tests/__init__.py
ppanini/tests/basic_tests_annotate_genes.py
ppanini/tests/basic_tests_ppanini.py
ppanini/tests/basic_tests_preppanini.py
ppanini/tests/basic_tests_quantify_genes.py
ppanini/tests/basic_tests_utilities.py
ppanini/tests/ppanini_test.py
ppanini/tests/test_config.py
ppanini/tests/data/__init__.py
ppanini/tests/data/demo.faa
ppanini/tests/data/demo.fna
ppanini/tests/data/demo.gff3
ppanini/tests/data/demo3.fasta
ppanini/tests/data/demo3_ppanini.log
ppanini/tests/data/demo3_ppanini.txt
ppanini/tests/data/demo3_ppanini_centroid_prev_abund.txt
ppanini/tests/data/demo3_ppanini_centroid_prev_abund_dict_all.txt
ppanini/tests/data/demo3_ppanini_centroid_prev_abund_ppanini_score_all.txt
ppanini/tests/data/demo3_ppanini_centroids.fasta
ppanini/tests/data/demo3_ppanini_clusters.uc
ppanini/tests/data/demo3_ppanini_gene_centroids_table.txt
ppanini/tests/data/demo3_ppanini_imp_centroid_prev_abund.txt
ppanini/tests/data/demo_test.faa
ppanini/tools/__init__.py
ppanini/tools/attach_lineage.py
ppanini/tools/compute_metagenomic_priority.py
ppanini/tools/fasta_select.py
ppanini/tools/graphlan_rings.py
ppanini/tools/plot_genome_hits.py
ppanini/tools/plot_prevalence_abundance.py
ppanini/tools/ppanini_barplot.py
ppanini/tools/ppanini_cluster2genes.py
ppanini/tools/ppanini_gene_caller.py
ppanini/tools/ppanini_infer_gene.py
ppanini/tools/ppanini_join_tables.py
ppanini/tools/ppanini_press.py
ppanini/tools/ppanini_rename_contigs.py
ppanini/tools/ppanini_rocplot.py
ppanini/tools/ppanini_scatterplot.py