Metadata-Version: 1.2
Name: ppanini
Version: 0.7.3.1
Summary: PPANINI: Prioritization and Prediction of functional Annotations for Novel and Important genes via automated data Network Integration.
Home-page: http://huttenhower.sph.harvard.edu/ppanini
Author: Gholamali Rahnavard, Afrah Shafquat, Eric A. Franzosa, and Curtis Huttenhower
Author-email: rahnavar@hsph.harvard.edu
Maintainer: Gholamali  Rahnavard
Maintainer-email: gholamali.rahnavard@gmail.com
License: MIT
Keywords: important,gene,prioritization,annotation
Platform: UNKNOWN
Classifier: Programming Language :: Python
Classifier: Development Status :: 5 - Production/Stable
Classifier: Environment :: Console
Classifier: Operating System :: MacOS
Classifier: Operating System :: Unix
Classifier: Programming Language :: Python
Classifier: Programming Language :: Python :: 2.7
Classifier: Topic :: Scientific/Engineering :: Bio-Informatics
